joom/__init__.py
joom/client.py
joom/oauth.py
joom/order.py
joom/product.py
joom/resource.py
joom/settings.py
joom/utils.py
joom/variation.py
joom_api-1.0.0.dist-info/DESCRIPTION.rst
joom_api-1.0.0.dist-info/METADATA
joom_api-1.0.0.dist-info/RECORD
joom_api-1.0.0.dist-info/WHEEL
joom_api-1.0.0.dist-info/metadata.json
joom_api-1.0.0.dist-info/top_level.txt
