Metadata-Version: 2.0
Name: joom-api
Version: 1.0.0
Summary: simple python joom merchant api client
Home-page: https://github.com/ketu/joom_api
Author: ketu.lai
Author-email: ketu.lai@gmail.com
License: MIT
Keywords: joom api
Platform: UNKNOWN
